[
    {
        "uuid": "0vp808-zs0xlg-e18x0s-wi21o0",
        "id": 42519,
        "origin": "提示.2psd",
        "output": "artboard-0vp808-zs0xlg-e18x0s-wi21o0.png",
        "detail": "detail-0vp808-zs0xlg-e18x0s-wi21o0.json",
        "platform": "web",
        "baseDpi": 2,
        "assets": {
            
        },
        "bounds": {
            "x": 0,
            "y": 0,
            "width": 2340,
            "height": 1440
        },
        "resolution": 72,
        "layers": [
            {
                "id": 0,
                "index": 0,
                "name": "提示.2psd",
                "type": "shapeLayer",
                "x": 0,
                "y": 0,
                "width": 2340,
                "height": 1440
            },
            {
                "id": 3200,
                "index": 25,
                "name": "ui_tishi_pic_jiantou_01",
                "type": "layer",
                "x": 1304,
                "y": 569,
                "width": 126,
                "height": 42,
                "opacity": 20
            },
            {
                "id": 3199,
                "index": 24,
                "name": "ui_common_icon_huobi_01",
                "type": "layer",
                "x": 1377,
                "y": 608,
                "width": 120,
                "height": 145,
                "opacity": 20
            },
            {
                "id": 3206,
                "index": 23,
                "name": "bg",
                "type": "layer",
                "x": 1362,
                "y": 204,
                "width": 326,
                "height": 75
            },
            {
                "id": 3039,
                "index": 22,
                "name": "UI_L_tishi_pic_juese_01",
                "type": "layer",
                "x": 798,
                "y": 451,
                "width": 228,
                "height": 193
            },
            {
                "id": 3164,
                "index": 21,
                "name": "ui_common_btn_X_01",
                "type": "layer",
                "x": 1442,
                "y": 470,
                "width": 88,
                "height": 89
            },
            {
                "id": 3167,
                "index": 20,
                "name": "xiegang",
                "type": "layer",
                "x": 820,
                "y": 446,
                "width": 688,
                "height": 196
            },
            {
                "id": 3166,
                "index": 19,
                "name": "UI_tishi_bak_shang_01",
                "type": "shapeLayer",
                "x": 819.938,
                "y": 446.5,
                "width": 696.062,
                "height": 195,
                "solidfill": {
                    "solid": {
                        "color": "#716552",
                        "opacity": 100,
                        "type": "solidfill"
                    }
                },
                "radius": [
                    45,
                    0,
                    0,
                    45
                ]
            },
            {
                "id": 3173,
                "index": 18,
                "name": "ui_common_icon_shipin_01",
                "type": "layer",
                "x": 1036,
                "y": 821,
                "width": 71,
                "height": 44
            },
            {
                "id": 3005,
                "index": 17,
                "name": "UI_loading_1_txt",
                "type": "textLayer",
                "x": 1362,
                "y": 864,
                "width": 36,
                "height": 25,
                "textInfo": {
                    "content": "-1",
                    "orientation": "horizontal",
                    "bounds": {
                        "x": -19.10107421875,
                        "y": -30.0698509216309,
                        "width": 38.2023620605469,
                        "height": 39.1933174133301
                    },
                    "fontPostScriptName": "MaokenAssortedSans",
                    "fontName": "MaokenAssortedSans",
                    "fontSize": 42,
                    "bold": false,
                    "italic": false,
                    "color": "#E6E3C9"
                }
            },
            {
                "id": 3201,
                "index": 16,
                "name": "ui_common_icon_huobi_01",
                "type": "layer",
                "x": 1319,
                "y": 859,
                "width": 30,
                "height": 38
            },
            {
                "id": 3041,
                "index": 15,
                "name": "ui_common_bak_btn_01",
                "type": "shapeLayer",
                "x": 1302.12,
                "y": 856,
                "width": 121.04,
                "height": 44,
                "solidfill": {
                    "solid": {
                        "color": "#413C33",
                        "opacity": 100,
                        "type": "solidfill"
                    }
                },
                "radius": [
                    22,
                    22,
                    22,
                    22
                ]
            },
            {
                "id": 3072,
                "index": 14,
                "name": "UI_tishi_icon_gou_01",
                "type": "shapeLayer",
                "x": 1151,
                "y": 862,
                "width": 34.03,
                "height": 34,
                "solidfill": {
                    "solid": {
                        "color": "#F5BB70",
                        "opacity": 100,
                        "type": "solidfill"
                    }
                },
                "radius": [
                    5,
                    5,
                    5,
                    5
                ]
            },
            {
                "id": 3172,
                "index": 13,
                "name": "UI_tishi_icon_X_01",
                "type": "shapeLayer",
                "x": 916.375,
                "y": 861.375,
                "width": 34.313,
                "height": 34.25,
                "solidfill": {
                    "solid": {
                        "color": "#7D786A",
                        "opacity": 100,
                        "type": "solidfill"
                    }
                },
                "radius": [
                    5.07965,
                    5.07965,
                    5.07965,
                    5.07965
                ]
            },
            {
                "id": 3055,
                "index": 12,
                "name": "UI_loading_2_txt",
                "type": "textLayer",
                "x": 992,
                "y": 863,
                "width": 55,
                "height": 30,
                "textInfo": {
                    "content": "No",
                    "orientation": "horizontal",
                    "bounds": {
                        "x": -27.0908203125,
                        "y": -36.09375,
                        "width": 54.181640625,
                        "height": 47.044921875
                    },
                    "fontPostScriptName": "MaokenAssortedSans",
                    "fontName": "MaokenAssortedSans",
                    "fontSize": 42,
                    "bold": false,
                    "italic": false,
                    "color": "#E6E3C9"
                }
            },
            {
                "id": 3054,
                "index": 11,
                "name": "UI_loading_3_txt",
                "type": "textLayer",
                "x": 1215,
                "y": 861,
                "width": 72,
                "height": 32,
                "textInfo": {
                    "content": "Yes",
                    "orientation": "horizontal",
                    "bounds": {
                        "x": -35.7239685058594,
                        "y": -36.09375,
                        "width": 71.0794372558594,
                        "height": 47.044921875
                    },
                    "fontPostScriptName": "MaokenAssortedSans",
                    "fontName": "MaokenAssortedSans",
                    "fontSize": 42,
                    "bold": false,
                    "italic": false,
                    "color": "#E6E3C9"
                }
            },
            {
                "id": 3169,
                "index": 10,
                "name": "ui_common_btn_black_01",
                "type": "layer",
                "x": 1125,
                "y": 834,
                "width": 324,
                "height": 97
            },
            {
                "id": 3170,
                "index": 9,
                "name": "ui_common_btn_black_01",
                "type": "layer",
                "x": 890,
                "y": 834,
                "width": 208,
                "height": 97
            },
            {
                "id": 2995,
                "index": 8,
                "name": "UI_loading_4_txt",
                "type": "textLayer",
                "x": 996,
                "y": 618,
                "width": 346,
                "height": 119,
                "textInfo": {
                    "content": "Consume\rto get a hint?",
                    "orientation": "horizontal",
                    "bounds": {
                        "x": 0,
                        "y": -7.42393112182617,
                        "width": 254.483215332031,
                        "height": 94.7483940124512
                    },
                    "fontPostScriptName": "Twinkly",
                    "fontName": "Twinkly",
                    "fontSize": 56,
                    "bold": false,
                    "italic": false,
                    "color": "#755341"
                }
            },
            {
                "id": 3207,
                "index": 7,
                "name": "UI_tishi_pic_tuya_01",
                "type": "layer",
                "x": 930,
                "y": 595,
                "width": 457,
                "height": 174
            },
            {
                "id": 3187,
                "index": 6,
                "name": "UI_common_bak_bian_01",
                "type": "layer",
                "x": 817,
                "y": 476,
                "width": 707,
                "height": 499
            },
            {
                "id": 3184,
                "index": 5,
                "name": "ui_common_bak_shang_01",
                "type": "layer",
                "x": 817,
                "y": 476,
                "width": 707,
                "height": 70
            },
            {
                "id": 3183,
                "index": 4,
                "name": "ui_common_pic_dian_01",
                "type": "shapeLayer",
                "x": 883,
                "y": 785,
                "width": 570.03,
                "height": 10,
                "solidfill": {
                    "solid": {
                        "color": "#CDD0B6",
                        "opacity": 100,
                        "type": "solidfill"
                    }
                },
                "stroke": {
                    "width": 10,
                    "color": "#CDD0B6",
                    "opacity": 100,
                    "alignment": "strokeStyleAlignCenter"
                }
            },
            {
                "id": 3182,
                "index": 3,
                "name": "ui_common_pic_xian_01",
                "type": "layer",
                "x": 817,
                "y": 476,
                "width": 707,
                "height": 492
            },
            {
                "id": 3186,
                "index": 2,
                "name": "ui_common_bak_xia_01",
                "type": "layer",
                "x": 817,
                "y": 476,
                "width": 707,
                "height": 492
            },
            {
                "id": 3077,
                "index": 1,
                "name": "UI_tishi_bak_diandi_01",
                "type": "shapeLayer",
                "x": 809.438,
                "y": 436,
                "width": 216.532,
                "height": 215.969,
                "solidfill": {
                    "solid": {
                        "color": "#EAECD8",
                        "opacity": 100,
                        "type": "solidfill"
                    }
                }
            },
            {
                "id": 2254,
                "index": 0,
                "name": "图层666",
                "type": "layer",
                "x": 0,
                "y": 0,
                "width": 2340,
                "height": 1440
            }
        ]
    }
]