[
    {
        "uuid": "rg2edl-72bxzr-5hkkj1-0yut5q",
        "id": 2395,
        "origin": "loading",
        "output": "artboard-rg2edl-72bxzr-5hkkj1-0yut5q.png",
        "detail": "detail-rg2edl-72bxzr-5hkkj1-0yut5q.json",
        "platform": "web",
        "baseDpi": 2,
        "assets": {
            
        },
        "bounds": {
            "x": 0,
            "y": 0,
            "width": 2340,
            "height": 1440
        },
        "resolution": 72,
        "layers": [
            {
                "id": 0,
                "index": 0,
                "name": "loading",
                "type": "shapeLayer",
                "x": 0,
                "y": 0,
                "width": 2340,
                "height": 1440
            },
            {
                "id": 3589,
                "index": 7,
                "name": "UI_loading_1_txt",
                "type": "textLayer",
                "x": 1069,
                "y": 1174,
                "width": 204,
                "height": 45,
                "textInfo": {
                    "content": "loading...",
                    "orientation": "horizontal",
                    "bounds": {
                        "x": -104.765625,
                        "y": -41.25,
                        "width": 209.53125,
                        "height": 53.765625
                    },
                    "fontPostScriptName": "MaokenAssortedSans",
                    "fontName": "MaokenAssortedSans",
                    "fontSize": 48,
                    "bold": false,
                    "italic": false,
                    "color": "#504A41"
                }
            },
            {
                "id": 3588,
                "index": 6,
                "name": "组31",
                "type": "layer",
                "x": 1620,
                "y": 1088,
                "width": 66,
                "height": 66
            },
            {
                "id": 3587,
                "index": 5,
                "name": "多边形3拷贝10",
                "type": "shapeLayer",
                "x": 1571.69,
                "y": 1101.69,
                "width": 65.47,
                "height": 34.6499999999999,
                "solidfill": {
                    "solid": {
                        "color": "#FFFFFF",
                        "opacity": 100,
                        "type": "solidfill"
                    }
                }
            },
            {
                "id": 3586,
                "index": 4,
                "name": "图层147",
                "type": "layer",
                "x": 1508,
                "y": 1099,
                "width": 145,
                "height": 44
            },
            {
                "id": 3591,
                "index": 3,
                "name": "UI_loading_bar_shang_01",
                "type": "layer",
                "x": 474,
                "y": 1099,
                "width": 1392,
                "height": 44
            },
            {
                "id": 3592,
                "index": 2,
                "name": "图层148",
                "type": "layer",
                "x": 470,
                "y": 1095,
                "width": 1400,
                "height": 58
            },
            {
                "id": 3566,
                "index": 1,
                "name": "UI_loading_bg_menghei_01",
                "type": "layer",
                "x": 0,
                "y": 0,
                "width": 2340,
                "height": 1440
            },
            {
                "id": 3314,
                "index": 0,
                "name": "biaoti",
                "type": "layer",
                "x": 0,
                "y": 0,
                "width": 2340,
                "height": 1440
            }
        ]
    }
]